rev_Baichuan/__init__.py
rev_Baichuan/chat.py
rev_baichuan-0.11.dist-info/LICENSE
rev_baichuan-0.11.dist-info/METADATA
rev_baichuan-0.11.dist-info/WHEEL
rev_baichuan-0.11.dist-info/top_level.txt
rev_baichuan-0.11.dist-info/RECORD
